{
  "metaData": {
    "File_name": "ST_01_Y20230830_T103353_CAM030000_Y02_f000065",
    "File_format": "jpg",
    "File_resolution": "1920x1080",
    "File_cam_ID": "cam03",
    "Game_date": "2023.08.30.10:33:53",
    "Game_weather": "cloudy",
    "Game_temperature(Celsius_degree)": "23",
    "Game_humidity(percent)": "84",
    "Game_wind_direction(degrees)": "258",
    "Game_wind_speed(m/s)": "1.9",
    "Player_height(cm)": "170~175",
    "Player_weight(Kg)": "70~75",
    "Player_grade": "L4",
    "Player_position": "batter",
    "Player_career(year)": "10~15",
    "Player_bats": "right",
    "Player_throws": "right",
    "Situation_umpire_judgement": "strike",
    "Situation_labeled_judgement": "strike",
    "Situation_code": "Y02",
    "Ball_labelname": "baseball_ball",
    "Ball_status": "defense",
    "License": "ComartsystemConsortium",
    "Version": "1.0",
    "Contributer": "ComartsystemConsortium",
    "Url": "AIHub",
    "sourcefile": "ST_01_Y20230830_T103353_CAM030000"
  },
  "annotation": [
    {
      "box": {
        "type": "box",
        "location": [
          {
            "x": 1016,
            "y": 663,
            "width": 104,
            "height": 35
          }
        ],
        "label": "Home_base"
      }
    },
    {
      "box": {
        "type": "box",
        "location": [
          {
            "x": 1664,
            "y": 453,
            "width": 169,
            "height": 328
          }
        ],
        "label": "Umpire1"
      }
    },
    {
      "box": {
        "type": "box",
        "location": [
          {
            "x": 1350,
            "y": 496,
            "width": 227,
            "height": 253
          }
        ],
        "label": "Catcher"
      }
    },
    {
      "box": {
        "type": "box",
        "location": [
          {
            "x": 1000,
            "y": 424,
            "width": 231,
            "height": 328
          }
        ],
        "label": "Batter"
      }
    },
    {
      "box": {
        "type": "box",
        "location": [
          {
            "x": 1297,
            "y": 549,
            "width": 25,
            "height": 16
          }
        ],
        "label": "Baseball_ball"
      }
    }
  ]
}